graphdatamodel/__init__.py
graphdatamodel/cli.py
graphdatamodel/graphdatamodel.py
graphdatamodel-0.1.0.dist-info/AUTHORS.rst
graphdatamodel-0.1.0.dist-info/LICENSE
graphdatamodel-0.1.0.dist-info/METADATA
graphdatamodel-0.1.0.dist-info/WHEEL
graphdatamodel-0.1.0.dist-info/entry_points.txt
graphdatamodel-0.1.0.dist-info/top_level.txt
graphdatamodel-0.1.0.dist-info/RECORD
